PyMCUlib/__init__.py
PyMCUlib/blend/__init__.py
PyMCUlib/blend/blend.py
PyMCUlib/contrast/__init__.py
PyMCUlib/contrast/contrast.py
PyMCUlib/dislike/__init__.py
PyMCUlib/dislike/dislike_analyzer.py
PyMCUlib/dynamiccolor/__init__.py
PyMCUlib/dynamiccolor/color_spec.py
PyMCUlib/dynamiccolor/color_spec_2021.py
PyMCUlib/dynamiccolor/color_spec_2025.py
PyMCUlib/dynamiccolor/color_spec_delegate.py
PyMCUlib/dynamiccolor/contrast_curve.py
PyMCUlib/dynamiccolor/dynamic_color.py
PyMCUlib/dynamiccolor/dynamic_scheme.py
PyMCUlib/dynamiccolor/material_dynamic_colors.py
PyMCUlib/dynamiccolor/tone_delta_pair.py
PyMCUlib/dynamiccolor/variant.py
PyMCUlib/hct/__init__.py
PyMCUlib/hct/cam16.py
PyMCUlib/hct/hct.py
PyMCUlib/hct/hct_solver.py
PyMCUlib/hct/viewing_conditions.py
PyMCUlib/palettes/__init__.py
PyMCUlib/palettes/core_palette.py
PyMCUlib/palettes/core_palettes.py
PyMCUlib/palettes/tonal_palette.py
PyMCUlib/quantize/__init__.py
PyMCUlib/quantize/lab_point_provider.py
PyMCUlib/quantize/point_provider.py
PyMCUlib/quantize/quantizer_celebi.py
PyMCUlib/quantize/quantizer_map.py
PyMCUlib/quantize/quantizer_wsmeans.py
PyMCUlib/quantize/quantizer_wu.py
PyMCUlib/scheme/__init__.py
PyMCUlib/scheme/scheme.py
PyMCUlib/scheme/scheme_android.py
PyMCUlib/scheme/scheme_content.py
PyMCUlib/scheme/scheme_expressive.py
PyMCUlib/scheme/scheme_fidelity.py
PyMCUlib/scheme/scheme_fruit_salad.py
PyMCUlib/scheme/scheme_monochrome.py
PyMCUlib/scheme/scheme_neutral.py
PyMCUlib/scheme/scheme_rainbow.py
PyMCUlib/scheme/scheme_tonal_spot.py
PyMCUlib/scheme/scheme_vibrant.py
PyMCUlib/score/__init__.py
PyMCUlib/score/score.py
PyMCUlib/temperature/__init__.py
PyMCUlib/temperature/temperature_cache.py
PyMCUlib/utils/__init__.py
PyMCUlib/utils/color_utils.py
PyMCUlib/utils/image_utils.py
PyMCUlib/utils/math_utils.py
PyMCUlib/utils/string_utils.py
PyMCUlib/utils/theme_utils.py
pymculib-1.0.3.dist-info/licenses/LICENSE.md
pymculib-1.0.3.dist-info/METADATA
pymculib-1.0.3.dist-info/WHEEL
pymculib-1.0.3.dist-info/top_level.txt
pymculib-1.0.3.dist-info/RECORD
