Metadata-Version: 2.4
Name: PyMCUlib
Version: 1.0.3
Summary: Material Color Utilities Python Library
Home-page: https://github.com/wenkang-deepblue/material-color-utilities-python
Author: Wenkang Li
Author-email: support@deepblue.cc
License: Apache-2.0
Classifier: Programming Language :: Python :: 3
Classifier: Programming Language :: Python :: 3.12
Classifier: Operating System :: OS Independent
Classifier: Topic :: Software Development :: Libraries
Classifier: Topic :: Multimedia :: Graphics
Requires-Python: >=3.12.0
License-File: LICENSE.md
Requires-Dist: numpy
Requires-Dist: pillow
Dynamic: author
Dynamic: author-email
Dynamic: classifier
Dynamic: description
Dynamic: description-content-type
Dynamic: home-page
Dynamic: license
Dynamic: license-file
Dynamic: requires-dist
Dynamic: requires-python
Dynamic: summary
